ingot_aws/__init__.py
ingot_aws/bootstrap/__init__.py
ingot_aws/bootstrap/scaffolding/__init__.py
ingot_aws/scripts/__init__.py
ingot_aws/scripts/ingot_aws.py
ingot_aws/tests/__init__.py
ingot_aws/tests/functionals/__init__.py
ingot_aws/tests/units/__init__.py
ingot_aws/tests/units/scripts/__init__.py
ingot_aws/tests/units/scripts/test_ingot_aws.py
scripts/__init__.py
scripts/create_package_version_file.py
ingot_aws-0.1.0.dist-info/LICENSE
ingot_aws-0.1.0.dist-info/METADATA
ingot_aws-0.1.0.dist-info/WHEEL
ingot_aws-0.1.0.dist-info/entry_points.txt
ingot_aws-0.1.0.dist-info/top_level.txt
ingot_aws-0.1.0.dist-info/RECORD
